snakemake_storage_plugin_gcs/__init__.py
snakemake_storage_plugin_gcs-1.1.4.dist-info/METADATA
snakemake_storage_plugin_gcs-1.1.4.dist-info/WHEEL
snakemake_storage_plugin_gcs-1.1.4.dist-info/licenses/LICENSE
snakemake_storage_plugin_gcs-1.1.4.dist-info/licenses/NOTICE
snakemake_storage_plugin_gcs-1.1.4.dist-info/RECORD
