Metadata-Version: 2.4
Name: snakemake-storage-plugin-gcs
Version: 1.1.4
Summary: A Snakemake storage plugin for Google Cloud Storage
Project-URL: repository, https://github.com/snakemake/snakemake-storage-plugin-gcs
Project-URL: documentation, https://snakemake.github.io/snakemake-plugin-catalog/plugins/storage/gcs.html
Author-email: Vanessa Sochat <sochat1@llnl.gov>, Johannes Koester <johannes.koester@uni-due.de>
License: MIT
License-File: LICENSE
License-File: NOTICE
Keywords: google cloud storage,plugin,snakemake,storage
Requires-Python: >=3.11
Requires-Dist: google-cloud-storage>=2.12.0
Requires-Dist: google-crc32c>=1.1.2
Requires-Dist: snakemake-interface-common>=1.14.2
Requires-Dist: snakemake-interface-storage-plugins>=4.0
